filter_data_options/__init__.py
filter_data_options/frontend/build/asset-manifest.json
filter_data_options/frontend/build/bootstrap.min.css
filter_data_options/frontend/build/index.html
filter_data_options/frontend/build/static/css/main.08a3b9c4.css
filter_data_options/frontend/build/static/css/main.08a3b9c4.css.map
filter_data_options/frontend/build/static/js/main.5ad8dc8e.js
filter_data_options/frontend/build/static/js/main.5ad8dc8e.js.LICENSE.txt
filter_data_options/frontend/build/static/js/main.5ad8dc8e.js.map
filter_data_options-0.0.5.dist-info/LICENSE
filter_data_options-0.0.5.dist-info/METADATA
filter_data_options-0.0.5.dist-info/WHEEL
filter_data_options-0.0.5.dist-info/top_level.txt
filter_data_options-0.0.5.dist-info/RECORD
