Metadata-Version: 2.1
Name: filter-data-options
Version: 0.0.5
Home-page: 
Author: 
Author-email: 
Requires-Python: >=3.7
License-File: LICENSE
Requires-Dist: streamlit (>=0.63)
